setup.py
tempyst/__init__.py
tempyst.egg-info/PKG-INFO
tempyst.egg-info/SOURCES.txt
tempyst.egg-info/dependency_links.txt
tempyst.egg-info/top_level.txt