Metadata-Version: 1.0
Name: tempyst
Version: 0.0.1
Summary: Utilities for temporary files and folders
Home-page: UNKNOWN
Author: Brian Lauber
Author-email: constructible.truth@gmail.com
License: UNKNOWN
Platform: UNKNOWN
